<?xml version="1.0" encoding="utf-8"?>
<list>
	<spawn name="[dion15_2122_01]">
		<mesh>
			<!-- [dion15_2122_01]	{{32971;135013;-3401;-2401};{37333;134255;-3401;-2401};{38373;136115;-3401;-2401};{33005;143452;-3401;-2401}} -->
			<vertex x="32971" y="135013" minz="-3401" maxz="-2401" />
			<vertex x="37333" y="134255" minz="-3401" maxz="-2401" />
			<vertex x="38373" y="136115" minz="-3401" maxz="-2401" />
			<vertex x="33005" y="143452" minz="-3401" maxz="-2401" />
		</mesh>
		<npc id="20205" count="5" respawn="24" />
		<!-- [dire_wolf]	pos=anywhere	total=5	respawn=24sec -->
		<npc id="20266" count="6" respawn="24" />
		<!-- [monstereye_gazer]	pos=anywhere	total=6	respawn=24sec -->
	</spawn>
	<spawn name="[dion15_2122_02]">
		<mesh>
			<!-- [dion15_2122_02]	{{37534;134310;-3567;-2667};{42190;133128;-3567;-2667};{44103;134234;-3567;-2667};{38581;136035;-3567;-2667}} -->
			<vertex x="37534" y="134310" minz="-3567" maxz="-2667" />
			<vertex x="42190" y="133128" minz="-3567" maxz="-2667" />
			<vertex x="44103" y="134234" minz="-3567" maxz="-2667" />
			<vertex x="38581" y="136035" minz="-3567" maxz="-2667" />
		</mesh>
		<npc id="20205" count="2" respawn="24" />
		<!-- [dire_wolf]	pos=anywhere	total=2	respawn=24sec -->
		<npc id="20266" count="4" respawn="24" />
		<!-- [monstereye_gazer]	pos=anywhere	total=4	respawn=24sec -->
	</spawn>
	<spawn name="[dion15_2122_03s]">
		<mesh>
			<!-- [dion15_2122_03s]	{{33268;136204;-3341;-2741};{35377;135291;-3341;-2741};{35754;137587;-3341;-2741};{33163;140018;-3341;-2741}} -->
			<vertex x="33268" y="136204" minz="-3341" maxz="-2741" />
			<vertex x="35377" y="135291" minz="-3341" maxz="-2741" />
			<vertex x="35754" y="137587" minz="-3341" maxz="-2741" />
			<vertex x="33163" y="140018" minz="-3341" maxz="-2741" />
		</mesh>
		<npc id="20265" count="2" respawn="24" />
		<!-- [monstereye_searcher]	pos=anywhere	total=2	respawn=24sec -->
		<npc id="20266" count="2" respawn="24" />
		<!-- [monstereye_gazer]	pos=anywhere	total=2	respawn=24sec -->
	</spawn>
	<spawn name="[dion02_2122_18]">
		<mesh>
			<!-- [dion02_2122_18]	{{40084;144588;-3861;-3061};{41708;146494;-3861;-3061};{40872;147701;-3861;-3061};{36518;147867;-3861;-3061};{37570;145419;-3861;-3061};{38709;144529;-3861;-3061}} -->
			<vertex x="40084" y="144588" minz="-3861" maxz="-3061" />
			<vertex x="41708" y="146494" minz="-3861" maxz="-3061" />
			<vertex x="40872" y="147701" minz="-3861" maxz="-3061" />
			<vertex x="36518" y="147867" minz="-3861" maxz="-3061" />
			<vertex x="37570" y="145419" minz="-3861" maxz="-3061" />
			<vertex x="38709" y="144529" minz="-3861" maxz="-3061" />
		</mesh>
		<npc id="20223" count="2" respawn="35" />
		<!-- [mandragora_sprout]	pos=anywhere	total=2	respawn=35sec -->
		<npc id="20154" count="4" respawn="35" />
		<!-- [manadragora]	pos=anywhere	total=4	respawn=35sec -->
	</spawn>
	<spawn name="[dion02_2122_19]">
		<mesh>
			<!-- [dion02_2122_19]	{{41756;149052;-3894;-3094};{41136;151006;-3894;-3094};{40160;151658;-3894;-3094};{38625;151563;-3894;-3094};{36644;150004;-3894;-3094};{36000;148753;-3894;-3094};{40615;148333;-3894;-3094}} -->
			<vertex x="41756" y="149052" minz="-3894" maxz="-3094" />
			<vertex x="41136" y="151006" minz="-3894" maxz="-3094" />
			<vertex x="40160" y="151658" minz="-3894" maxz="-3094" />
			<vertex x="38625" y="151563" minz="-3894" maxz="-3094" />
			<vertex x="36644" y="150004" minz="-3894" maxz="-3094" />
			<vertex x="36000" y="148753" minz="-3894" maxz="-3094" />
			<vertex x="40615" y="148333" minz="-3894" maxz="-3094" />
		</mesh>
		<npc id="20223" count="2" respawn="35" />
		<!-- [mandragora_sprout]	pos=anywhere	total=2	respawn=35sec -->
		<npc id="20154" count="4" respawn="35" />
		<!-- [manadragora]	pos=anywhere	total=4	respawn=35sec -->
	</spawn>
	<spawn name="[dion02_2122_20s]">
		<mesh>
			<!-- [dion02_2122_20s]	{{40207;145191;-3960;-3360};{41090;146457;-3960;-3360};{40727;147323;-3960;-3360};{38391;147509;-3960;-3360};{38314;146511;-3960;-3360};{39653;145086;-3960;-3360}} -->
			<vertex x="40207" y="145191" minz="-3960" maxz="-3360" />
			<vertex x="41090" y="146457" minz="-3960" maxz="-3360" />
			<vertex x="40727" y="147323" minz="-3960" maxz="-3360" />
			<vertex x="38391" y="147509" minz="-3960" maxz="-3360" />
			<vertex x="38314" y="146511" minz="-3960" maxz="-3360" />
			<vertex x="39653" y="145086" minz="-3960" maxz="-3360" />
		</mesh>
		<npc id="20155" count="2" respawn="35" />
		<!-- [mandragora_a]	pos=anywhere	total=2	respawn=35sec -->
		<npc id="20156" count="3" respawn="35" />
		<!-- [mandragora_b]	pos=anywhere	total=3	respawn=35sec -->
	</spawn>
	<spawn name="[dion02_2122_21s]">
		<mesh>
			<!-- [dion02_2122_21s]	{{40684;148647;-3960;-3360};{41166;149292;-3960;-3360};{40777;150866;-3960;-3360};{39042;150811;-3960;-3360};{37668;149673;-3960;-3360};{38100;149070;-3960;-3360}} -->
			<vertex x="40684" y="148647" minz="-3960" maxz="-3360" />
			<vertex x="41166" y="149292" minz="-3960" maxz="-3360" />
			<vertex x="40777" y="150866" minz="-3960" maxz="-3360" />
			<vertex x="39042" y="150811" minz="-3960" maxz="-3360" />
			<vertex x="37668" y="149673" minz="-3960" maxz="-3360" />
			<vertex x="38100" y="149070" minz="-3960" maxz="-3360" />
		</mesh>
		<npc id="20155" count="3" respawn="35" />
		<!-- [mandragora_a]	pos=anywhere	total=3	respawn=35sec -->
		<npc id="20156" count="2" respawn="35" />
		<!-- [mandragora_b]	pos=anywhere	total=2	respawn=35sec -->
	</spawn>
	<spawn name="[dion02_2122_22]">
		<mesh>
			<!-- [dion02_2122_22]	{{42496;145978;-3926;-3326};{44081;145641;-3926;-3326};{45769;150508;-3926;-3326};{43954;151455;-3926;-3326};{41966;151078;-3926;-3326}} -->
			<vertex x="42496" y="145978" minz="-3926" maxz="-3326" />
			<vertex x="44081" y="145641" minz="-3926" maxz="-3326" />
			<vertex x="45769" y="150508" minz="-3926" maxz="-3326" />
			<vertex x="43954" y="151455" minz="-3926" maxz="-3326" />
			<vertex x="41966" y="151078" minz="-3926" maxz="-3326" />
		</mesh>
		<npc id="20201" count="5" respawn="35" />
		<!-- [ghoul]	pos=anywhere	total=5	respawn=35sec -->
		<npc id="20083" count="5" respawn="35" />
		<!-- [granitic_golem]	pos=anywhere	total=5	respawn=35sec -->
		<npc id="20202" count="5" respawn="35" />
		<!-- [dead_seeker]	pos=anywhere	total=5	respawn=35sec -->
	</spawn>
	<spawn name="[dion02_2122_23]">
		<mesh>
			<!-- [dion02_2122_23]	{{42857;141840;-3383;-2783};{45622;140341;-3383;-2783};{49682;140637;-3383;-2783};{43661;144493;-3383;-2783};{42221;144692;-3383;-2783};{41750;143115;-3383;-2783}} -->
			<vertex x="42857" y="141840" minz="-3383" maxz="-2783" />
			<vertex x="45622" y="140341" minz="-3383" maxz="-2783" />
			<vertex x="49682" y="140637" minz="-3383" maxz="-2783" />
			<vertex x="43661" y="144493" minz="-3383" maxz="-2783" />
			<vertex x="42221" y="144692" minz="-3383" maxz="-2783" />
			<vertex x="41750" y="143115" minz="-3383" maxz="-2783" />
		</mesh>
		<npc id="20160" count="4" respawn="35" />
		<!-- [neer_crawler]	pos=anywhere	total=4	respawn=35sec -->
		<npc id="20198" count="4" respawn="35" />
		<!-- [neer_crawler_frak]	pos=anywhere	total=4	respawn=35sec -->
		<npc id="20199" count="6" respawn="35" />
		<!-- [amber_basilisk]	pos=anywhere	total=6	respawn=35sec -->
		<npc id="20200" count="6" respawn="35" />
		<!-- [strain]	pos=anywhere	total=6	respawn=35sec -->
	</spawn>
	<spawn name="[dion02_2122_24]">
		<mesh>
			<!-- [dion02_2122_24]	{{44744;145274;-3838;-3238};{48911;142988;-3838;-3238};{50804;145462;-3838;-3238};{47162;146946;-3838;-3238};{45026;146381;-3838;-3238}} -->
			<vertex x="44744" y="145274" minz="-3838" maxz="-3238" />
			<vertex x="48911" y="142988" minz="-3838" maxz="-3238" />
			<vertex x="50804" y="145462" minz="-3838" maxz="-3238" />
			<vertex x="47162" y="146946" minz="-3838" maxz="-3238" />
			<vertex x="45026" y="146381" minz="-3838" maxz="-3238" />
		</mesh>
		<npc id="20083" count="4" respawn="35" />
		<!-- [granitic_golem]	pos=anywhere	total=4	respawn=35sec -->
		<npc id="20202" count="4" respawn="35" />
		<!-- [dead_seeker]	pos=anywhere	total=4	respawn=35sec -->
		<npc id="20144" count="6" respawn="35" />
		<!-- [hanged_man_ripper]	pos=anywhere	total=6	respawn=35sec -->
	</spawn>
	<spawn name="[dion02_2122_25]">
		<mesh>
			<!-- [dion02_2122_25]	{{44980;146491;-3838;-3238};{47143;146996;-3838;-3238};{48372;149913;-3838;-3238};{46505;149937;-3838;-3238};{45052;148251;-3838;-3238}} -->
			<vertex x="44980" y="146491" minz="-3838" maxz="-3238" />
			<vertex x="47143" y="146996" minz="-3838" maxz="-3238" />
			<vertex x="48372" y="149913" minz="-3838" maxz="-3238" />
			<vertex x="46505" y="149937" minz="-3838" maxz="-3238" />
			<vertex x="45052" y="148251" minz="-3838" maxz="-3238" />
		</mesh>
		<npc id="20201" count="2" respawn="35" />
		<!-- [ghoul]	pos=anywhere	total=2	respawn=35sec -->
		<npc id="20083" count="2" respawn="35" />
		<!-- [granitic_golem]	pos=anywhere	total=2	respawn=35sec -->
		<npc id="20202" count="2" respawn="35" />
		<!-- [dead_seeker]	pos=anywhere	total=2	respawn=35sec -->
	</spawn>
	<spawn name="[dion02_2122_26]">
		<mesh>
			<!-- [dion02_2122_26]	{{47199;146990;-3838;-3238};{50752;145592;-3838;-3238};{51469;146809;-3838;-3238};{50099;148622;-3838;-3238};{48427;149892;-3838;-3238}} -->
			<vertex x="47199" y="146990" minz="-3838" maxz="-3238" />
			<vertex x="50752" y="145592" minz="-3838" maxz="-3238" />
			<vertex x="51469" y="146809" minz="-3838" maxz="-3238" />
			<vertex x="50099" y="148622" minz="-3838" maxz="-3238" />
			<vertex x="48427" y="149892" minz="-3838" maxz="-3238" />
		</mesh>
		<npc id="20201" count="3" respawn="35" />
		<!-- [ghoul]	pos=anywhere	total=3	respawn=35sec -->
		<npc id="20202" count="3" respawn="35" />
		<!-- [dead_seeker]	pos=anywhere	total=3	respawn=35sec -->
		<npc id="20144" count="3" respawn="35" />
		<!-- [hanged_man_ripper]	pos=anywhere	total=3	respawn=35sec -->
	</spawn>
	<spawn name="[dion02_2122_27]">
		<mesh>
			<!-- [dion02_2122_27]	{{42902;152504;-2950;-2450};{44936;152332;-2950;-2450};{45636;153902;-2950;-2450};{45367;154535;-2950;-2450};{44044;155256;-2950;-2450}} -->
			<vertex x="42902" y="152504" minz="-2950" maxz="-2450" />
			<vertex x="44936" y="152332" minz="-2950" maxz="-2450" />
			<vertex x="45636" y="153902" minz="-2950" maxz="-2450" />
			<vertex x="45367" y="154535" minz="-2950" maxz="-2450" />
			<vertex x="44044" y="155256" minz="-2950" maxz="-2450" />
		</mesh>
		<npc id="20199" count="2" respawn="35" />
		<!-- [amber_basilisk]	pos=anywhere	total=2	respawn=35sec -->
		<npc id="20200" count="2" respawn="35" />
		<!-- [strain]	pos=anywhere	total=2	respawn=35sec -->
		<npc id="20202" count="3" respawn="35" />
		<!-- [dead_seeker]	pos=anywhere	total=3	respawn=35sec -->
	</spawn>
	<spawn name="[dion02_2122_29]">
		<mesh>
			<!-- [dion02_2122_29]	{{45699;151349;-2946;-2446};{48307;150431;-2946;-2446};{50400;154088;-2946;-2446};{47523;155433;-2946;-2446};{46010;154313;-2946;-2446};{44995;152326;-2946;-2446}} -->
			<vertex x="45699" y="151349" minz="-2946" maxz="-2446" />
			<vertex x="48307" y="150431" minz="-2946" maxz="-2446" />
			<vertex x="50400" y="154088" minz="-2946" maxz="-2446" />
			<vertex x="47523" y="155433" minz="-2946" maxz="-2446" />
			<vertex x="46010" y="154313" minz="-2946" maxz="-2446" />
			<vertex x="44995" y="152326" minz="-2946" maxz="-2446" />
		</mesh>
		<npc id="20160" count="7" respawn="35" />
		<!-- [neer_crawler]	pos=anywhere	total=7	respawn=35sec -->
		<npc id="20198" count="7" respawn="35" />
		<!-- [neer_crawler_frak]	pos=anywhere	total=7	respawn=35sec -->
	</spawn>
	<spawn name="[dion02_2122_30]">
		<mesh>
			<!-- [dion02_2122_30]	{{48695;149982;-3636;-3136};{49276;149854;-3636;-3136};{50752;152014;-3636;-3136};{50233;152340;-3636;-3136}} -->
			<vertex x="48695" y="149982" minz="-3636" maxz="-3136" />
			<vertex x="49276" y="149854" minz="-3636" maxz="-3136" />
			<vertex x="50752" y="152014" minz="-3636" maxz="-3136" />
			<vertex x="50233" y="152340" minz="-3636" maxz="-3136" />
		</mesh>
		<npc id="20200" count="2" respawn="35" />
		<!-- [strain]	pos=anywhere	total=2	respawn=35sec -->
		<npc id="20202" count="1" respawn="35" />
		<!-- [dead_seeker]	pos=anywhere	total=1	respawn=35sec -->
	</spawn>
	<spawn name="[dion02_2122_31]">
		<mesh>
			<!-- [dion02_2122_31]	{{50625;152619;-3636;-3136};{50943;152432;-3636;-3136};{52288;154355;-3636;-3136};{51244;155096;-3636;-3136}} -->
			<vertex x="50625" y="152619" minz="-3636" maxz="-3136" />
			<vertex x="50943" y="152432" minz="-3636" maxz="-3136" />
			<vertex x="52288" y="154355" minz="-3636" maxz="-3136" />
			<vertex x="51244" y="155096" minz="-3636" maxz="-3136" />
		</mesh>
		<npc id="20200" count="2" respawn="35" />
		<!-- [strain]	pos=anywhere	total=2	respawn=35sec -->
		<npc id="20202" count="2" respawn="35" />
		<!-- [dead_seeker]	pos=anywhere	total=2	respawn=35sec -->
	</spawn>
	<spawn name="[dion02_2122_32]">
		<mesh>
			<!-- [dion02_2122_32]	{{55469;149586;-2582;-2082};{56313;152034;-2582;-2082};{54503;154048;-2582;-2082};{53433;153653;-2582;-2082};{50028;149894;-2582;-2082};{52371;147614;-2582;-2082}} -->
			<vertex x="55469" y="149586" minz="-2582" maxz="-2082" />
			<vertex x="56313" y="152034" minz="-2582" maxz="-2082" />
			<vertex x="54503" y="154048" minz="-2582" maxz="-2082" />
			<vertex x="53433" y="153653" minz="-2582" maxz="-2082" />
			<vertex x="50028" y="149894" minz="-2582" maxz="-2082" />
			<vertex x="52371" y="147614" minz="-2582" maxz="-2082" />
		</mesh>
		<npc id="20171" count="5" respawn="35" />
		<!-- [specter]	pos=anywhere	total=5	respawn=35sec -->
		<npc id="20197" count="4" respawn="35" />
		<!-- [lemures]	pos=anywhere	total=4	respawn=35sec -->
		<npc id="20160" count="6" respawn="35" />
		<!-- [neer_crawler]	pos=anywhere	total=6	respawn=35sec -->
	</spawn>
	<spawn name="[dion02_2122_33]">
		<mesh>
			<!-- [dion02_2122_33]	{{51744;145023;-3253;-2453};{56485;145730;-3253;-2453};{56270;148733;-3253;-2453};{52646;146960;-3253;-2453}} -->
			<vertex x="51744" y="145023" minz="-3253" maxz="-2453" />
			<vertex x="56485" y="145730" minz="-3253" maxz="-2453" />
			<vertex x="56270" y="148733" minz="-3253" maxz="-2453" />
			<vertex x="52646" y="146960" minz="-3253" maxz="-2453" />
		</mesh>
		<npc id="20171" count="4" respawn="35" />
		<!-- [specter]	pos=anywhere	total=4	respawn=35sec -->
		<npc id="20197" count="5" respawn="35" />
		<!-- [lemures]	pos=anywhere	total=5	respawn=35sec -->
	</spawn>
	<spawn name="[dion02_2122_34]">
		<mesh>
			<!-- [dion02_2122_34]	{{56056;142591;-3253;-2553};{57137;144898;-3253;-2553};{56736;145705;-3253;-2553};{54656;145335;-3253;-2553}} -->
			<vertex x="56056" y="142591" minz="-3253" maxz="-2553" />
			<vertex x="57137" y="144898" minz="-3253" maxz="-2553" />
			<vertex x="56736" y="145705" minz="-3253" maxz="-2553" />
			<vertex x="54656" y="145335" minz="-3253" maxz="-2553" />
		</mesh>
		<npc id="20171" count="3" respawn="35" />
		<!-- [specter]	pos=anywhere	total=3	respawn=35sec -->
		<npc id="20197" count="2" respawn="35" />
		<!-- [lemures]	pos=anywhere	total=2	respawn=35sec -->
	</spawn>
	<spawn name="[dion02_2122_35]">
		<mesh>
			<!-- [dion02_2122_35]	{{55936;140654;-3241;-2541};{56037;142496;-3241;-2541};{55434;143702;-3241;-2541};{54370;142282;-3241;-2541}} -->
			<vertex x="55936" y="140654" minz="-3241" maxz="-2541" />
			<vertex x="56037" y="142496" minz="-3241" maxz="-2541" />
			<vertex x="55434" y="143702" minz="-3241" maxz="-2541" />
			<vertex x="54370" y="142282" minz="-3241" maxz="-2541" />
		</mesh>
		<npc id="20156" count="2" respawn="35" />
		<!-- [mandragora_b]	pos=anywhere	total=2	respawn=35sec -->
		<npc id="20171" count="2" respawn="35" />
		<!-- [specter]	pos=anywhere	total=2	respawn=35sec -->
	</spawn>
	<spawn name="[dion02_2122_36]">
		<mesh>
			<!-- [dion02_2122_36]	{{55871;140644;-3220;-2520};{54432;142155;-3220;-2520};{52211;142380;-3220;-2520};{51821;141491;-3220;-2520};{52875;140482;-3220;-2520}} -->
			<vertex x="55871" y="140644" minz="-3220" maxz="-2520" />
			<vertex x="54432" y="142155" minz="-3220" maxz="-2520" />
			<vertex x="52211" y="142380" minz="-3220" maxz="-2520" />
			<vertex x="51821" y="141491" minz="-3220" maxz="-2520" />
			<vertex x="52875" y="140482" minz="-3220" maxz="-2520" />
		</mesh>
		<npc id="20156" count="2" respawn="35" />
		<!-- [mandragora_b]	pos=anywhere	total=2	respawn=35sec -->
		<npc id="20171" count="3" respawn="35" />
		<!-- [specter]	pos=anywhere	total=3	respawn=35sec -->
	</spawn>
	<spawn name="[dion02_2122_37]">
		<mesh>
			<!-- [dion02_2122_37]	{{51970;141788;-3284;-2684};{52534;145286;-3284;-2684};{51402;145031;-3284;-2684};{50727;143813;-3284;-2684};{51223;142359;-3284;-2684}} -->
			<vertex x="51970" y="141788" minz="-3284" maxz="-2684" />
			<vertex x="52534" y="145286" minz="-3284" maxz="-2684" />
			<vertex x="51402" y="145031" minz="-3284" maxz="-2684" />
			<vertex x="50727" y="143813" minz="-3284" maxz="-2684" />
			<vertex x="51223" y="142359" minz="-3284" maxz="-2684" />
		</mesh>
		<npc id="20171" count="3" respawn="35" />
		<!-- [specter]	pos=anywhere	total=3	respawn=35sec -->
		<npc id="20197" count="2" respawn="35" />
		<!-- [lemures]	pos=anywhere	total=2	respawn=35sec -->
	</spawn>
	<spawn name="[dion02_2122_38s]">
		<mesh>
			<!-- [dion02_2122_38s]	{{42853;146471;-3767;-3267};{43925;146306;-3767;-3267};{44304;147633;-3767;-3267};{42672;147706;-3767;-3267}} -->
			<vertex x="42853" y="146471" minz="-3767" maxz="-3267" />
			<vertex x="43925" y="146306" minz="-3767" maxz="-3267" />
			<vertex x="44304" y="147633" minz="-3767" maxz="-3267" />
			<vertex x="42672" y="147706" minz="-3767" maxz="-3267" />
		</mesh>
		<npc id="20200" count="2" respawn="35" />
		<!-- [strain]	pos=anywhere	total=2	respawn=35sec -->
	</spawn>
	<spawn name="[dion02_2122_39s]">
		<mesh>
			<!-- [dion02_2122_39s]	{{42663;149260;-3834;-3334};{44673;149064;-3834;-3334};{45296;150317;-3834;-3334};{42804;150828;-3834;-3334}} -->
			<vertex x="42663" y="149260" minz="-3834" maxz="-3334" />
			<vertex x="44673" y="149064" minz="-3834" maxz="-3334" />
			<vertex x="45296" y="150317" minz="-3834" maxz="-3334" />
			<vertex x="42804" y="150828" minz="-3834" maxz="-3334" />
		</mesh>
		<npc id="20201" count="2" respawn="35" />
		<!-- [ghoul]	pos=anywhere	total=2	respawn=35sec -->
	</spawn>
	<spawn name="[dion02_2122_40s]">
		<mesh>
			<!-- [dion02_2122_40s]	{{45398;145106;-3805;-3305};{47076;144403;-3805;-3305};{48104;146247;-3805;-3305};{46546;146341;-3805;-3305}} -->
			<vertex x="45398" y="145106" minz="-3805" maxz="-3305" />
			<vertex x="47076" y="144403" minz="-3805" maxz="-3305" />
			<vertex x="48104" y="146247" minz="-3805" maxz="-3305" />
			<vertex x="46546" y="146341" minz="-3805" maxz="-3305" />
		</mesh>
		<npc id="20201" count="2" respawn="35" />
		<!-- [ghoul]	pos=anywhere	total=2	respawn=35sec -->
		<npc id="20144" count="2" respawn="35" />
		<!-- [hanged_man_ripper]	pos=anywhere	total=2	respawn=35sec -->
	</spawn>
	<spawn name="[dion02_2122_41s]">
		<mesh>
			<!-- [dion02_2122_41s]	{{47681;144020;-3802;-3302};{48911;143887;-3802;-3302};{50086;145330;-3802;-3302};{48755;145724;-3802;-3302}} -->
			<vertex x="47681" y="144020" minz="-3802" maxz="-3302" />
			<vertex x="48911" y="143887" minz="-3802" maxz="-3302" />
			<vertex x="50086" y="145330" minz="-3802" maxz="-3302" />
			<vertex x="48755" y="145724" minz="-3802" maxz="-3302" />
		</mesh>
		<npc id="20202" count="2" respawn="35" />
		<!-- [dead_seeker]	pos=anywhere	total=2	respawn=35sec -->
		<npc id="20144" count="2" respawn="35" />
		<!-- [hanged_man_ripper]	pos=anywhere	total=2	respawn=35sec -->
	</spawn>
	<spawn name="[dion02_2122_42s]">
		<mesh>
			<!-- [dion02_2122_42s]	{{45323;147125;-3831;-3331};{46906;147752;-3831;-3331};{47803;149189;-3831;-3331};{46455;149499;-3831;-3331}} -->
			<vertex x="45323" y="147125" minz="-3831" maxz="-3331" />
			<vertex x="46906" y="147752" minz="-3831" maxz="-3331" />
			<vertex x="47803" y="149189" minz="-3831" maxz="-3331" />
			<vertex x="46455" y="149499" minz="-3831" maxz="-3331" />
		</mesh>
		<npc id="20200" count="3" respawn="35" />
		<!-- [strain]	pos=anywhere	total=3	respawn=35sec -->
	</spawn>
	<spawn name="[dion02_2122_43s]">
		<mesh>
			<!-- [dion02_2122_43s]	{{49251;146451;-3683;-3183};{50449;146123;-3683;-3183};{51130;147001;-3683;-3183};{49994;148234;-3683;-3183}} -->
			<vertex x="49251" y="146451" minz="-3683" maxz="-3183" />
			<vertex x="50449" y="146123" minz="-3683" maxz="-3183" />
			<vertex x="51130" y="147001" minz="-3683" maxz="-3183" />
			<vertex x="49994" y="148234" minz="-3683" maxz="-3183" />
		</mesh>
		<npc id="20144" count="3" respawn="35" />
		<!-- [hanged_man_ripper]	pos=anywhere	total=3	respawn=35sec -->
	</spawn>
	<spawn name="[dion02_2122_44s]">
		<mesh>
			<!-- [dion02_2122_44s]	{{45393;152293;-2923;-2423};{45869;151501;-2923;-2423};{47061;151446;-2923;-2423};{46457;153897;-2923;-2423}} -->
			<vertex x="45393" y="152293" minz="-2923" maxz="-2423" />
			<vertex x="45869" y="151501" minz="-2923" maxz="-2423" />
			<vertex x="47061" y="151446" minz="-2923" maxz="-2423" />
			<vertex x="46457" y="153897" minz="-2923" maxz="-2423" />
		</mesh>
		<npc id="20144" count="3" respawn="35" />
		<!-- [hanged_man_ripper]	pos=anywhere	total=3	respawn=35sec -->
	</spawn>
	<spawn name="[dion02_2122_45s]">
		<mesh>
			<!-- [dion02_2122_45s]	{{46917;153602;-2923;-2423};{47305;151737;-2923;-2423};{48169;151879;-2923;-2423};{47785;153810;-2923;-2423}} -->
			<vertex x="46917" y="153602" minz="-2923" maxz="-2423" />
			<vertex x="47305" y="151737" minz="-2923" maxz="-2423" />
			<vertex x="48169" y="151879" minz="-2923" maxz="-2423" />
			<vertex x="47785" y="153810" minz="-2923" maxz="-2423" />
		</mesh>
		<npc id="20202" count="2" respawn="35" />
		<!-- [dead_seeker]	pos=anywhere	total=2	respawn=35sec -->
	</spawn>
	<spawn name="[dion02_2122_46s]">
		<mesh>
			<!-- [dion02_2122_46s]	{{47291;154950;-2923;-2423};{46822;153717;-2923;-2423};{49306;152389;-2923;-2423};{49623;154238;-2923;-2423}} -->
			<vertex x="47291" y="154950" minz="-2923" maxz="-2423" />
			<vertex x="46822" y="153717" minz="-2923" maxz="-2423" />
			<vertex x="49306" y="152389" minz="-2923" maxz="-2423" />
			<vertex x="49623" y="154238" minz="-2923" maxz="-2423" />
		</mesh>
		<npc id="20201" count="2" respawn="35" />
		<!-- [ghoul]	pos=anywhere	total=2	respawn=35sec -->
		<npc id="20198" count="2" respawn="35" />
		<!-- [neer_crawler_frak]	pos=anywhere	total=2	respawn=35sec -->
	</spawn>
	<spawn name="[dion02_2122_47s]">
		<mesh>
			<!-- [dion02_2122_47s]	{{42840;144248;-3382;-2882};{42175;142912;-3382;-2882};{43578;141816;-3382;-2882};{44281;143644;-3382;-2882}} -->
			<vertex x="42840" y="144248" minz="-3382" maxz="-2882" />
			<vertex x="42175" y="142912" minz="-3382" maxz="-2882" />
			<vertex x="43578" y="141816" minz="-3382" maxz="-2882" />
			<vertex x="44281" y="143644" minz="-3382" maxz="-2882" />
		</mesh>
		<npc id="20144" count="2" respawn="35" />
		<!-- [hanged_man_ripper]	pos=anywhere	total=2	respawn=35sec -->
	</spawn>
	<spawn name="[dion02_2122_48s]">
		<mesh>
			<!-- [dion02_2122_48s]	{{44505;143300;-3382;-2882};{43840;141964;-3382;-2882};{45243;140869;-3382;-2882};{45946;142696;-3382;-2882}} -->
			<vertex x="44505" y="143300" minz="-3382" maxz="-2882" />
			<vertex x="43840" y="141964" minz="-3382" maxz="-2882" />
			<vertex x="45243" y="140869" minz="-3382" maxz="-2882" />
			<vertex x="45946" y="142696" minz="-3382" maxz="-2882" />
		</mesh>
		<npc id="20202" count="2" respawn="35" />
		<!-- [dead_seeker]	pos=anywhere	total=2	respawn=35sec -->
	</spawn>
	<spawn name="[dion02_2122_49s]">
		<mesh>
			<!-- [dion02_2122_49s]	{{46453;142389;-3382;-2882};{45613;140687;-3382;-2882};{46892;140601;-3382;-2882};{47951;141249;-3382;-2882}} -->
			<vertex x="46453" y="142389" minz="-3382" maxz="-2882" />
			<vertex x="45613" y="140687" minz="-3382" maxz="-2882" />
			<vertex x="46892" y="140601" minz="-3382" maxz="-2882" />
			<vertex x="47951" y="141249" minz="-3382" maxz="-2882" />
		</mesh>
		<npc id="20200" count="2" respawn="35" />
		<!-- [strain]	pos=anywhere	total=2	respawn=35sec -->
	</spawn>
	<spawn name="[dion02_2122_50s]">
		<mesh>
			<!-- [dion02_2122_50s]	{{51784;151099;-2584;-2084};{51063;149673;-2584;-2084};{52598;148486;-2584;-2084};{54839;149446;-2584;-2084}} -->
			<vertex x="51784" y="151099" minz="-2584" maxz="-2084" />
			<vertex x="51063" y="149673" minz="-2584" maxz="-2084" />
			<vertex x="52598" y="148486" minz="-2584" maxz="-2084" />
			<vertex x="54839" y="149446" minz="-2584" maxz="-2084" />
		</mesh>
		<npc id="20200" count="3" respawn="35" />
		<!-- [strain]	pos=anywhere	total=3	respawn=35sec -->
	</spawn>
	<spawn name="[dion02_2122_51s]">
		<mesh>
			<!-- [dion02_2122_51s]	{{53951;153066;-2584;-2084};{52204;151589;-2584;-2084};{54971;150128;-2584;-2084};{55574;151607;-2584;-2084}} -->
			<vertex x="53951" y="153066" minz="-2584" maxz="-2084" />
			<vertex x="52204" y="151589" minz="-2584" maxz="-2084" />
			<vertex x="54971" y="150128" minz="-2584" maxz="-2084" />
			<vertex x="55574" y="151607" minz="-2584" maxz="-2084" />
		</mesh>
		<npc id="20198" count="2" respawn="35" />
		<!-- [neer_crawler_frak]	pos=anywhere	total=2	respawn=35sec -->
	</spawn>
	<spawn name="[dion02_2122_52s]">
		<mesh>
			<!-- [dion02_2122_52s]	{{53620;146977;-3185;-2685};{52769;145630;-3185;-2685};{55479;145695;-3185;-2685};{55648;147230;-3185;-2685}} -->
			<vertex x="53620" y="146977" minz="-3185" maxz="-2685" />
			<vertex x="52769" y="145630" minz="-3185" maxz="-2685" />
			<vertex x="55479" y="145695" minz="-3185" maxz="-2685" />
			<vertex x="55648" y="147230" minz="-3185" maxz="-2685" />
		</mesh>
		<npc id="20160" count="2" respawn="35" />
		<!-- [neer_crawler]	pos=anywhere	total=2	respawn=35sec -->
	</spawn>
	<spawn name="[dion02_2122_53s]">
		<mesh>
			<!-- [dion02_2122_53s]	{{52848;142049;-3185;-2685};{52509;141197;-3185;-2685};{54600;140953;-3185;-2685};{54391;141851;-3185;-2685}} -->
			<vertex x="52848" y="142049" minz="-3185" maxz="-2685" />
			<vertex x="52509" y="141197" minz="-3185" maxz="-2685" />
			<vertex x="54600" y="140953" minz="-3185" maxz="-2685" />
			<vertex x="54391" y="141851" minz="-3185" maxz="-2685" />
		</mesh>
		<npc id="20197" count="2" respawn="35" />
		<!-- [lemures]	pos=anywhere	total=2	respawn=35sec -->
	</spawn>
	<spawn name="[dion13_2122_01]">
		<mesh>
			<!-- [dion13_2122_01]	{{34507;162123;-3869;-2869};{41523;161005;-3869;-2869};{42133;163614;-3869;-2869};{32934;163587;-3869;-2869}} -->
			<vertex x="34507" y="162123" minz="-3869" maxz="-2869" />
			<vertex x="41523" y="161005" minz="-3869" maxz="-2869" />
			<vertex x="42133" y="163614" minz="-3869" maxz="-2869" />
			<vertex x="32934" y="163587" minz="-3869" maxz="-2869" />
		</mesh>
		<npc id="20939" count="10" respawn="45" />
		<!-- [tanor_silenos_warrior]	pos=anywhere	total=10	respawn=45sec	Privates=[tanor_silenos_scout:tanor_silenos_scout:1:0sec;tanor_silenos_grunt:tanor_silenos_grunt:1:0sec;tanor_silenos:tanor_silenos:1:0sec] -->
	</spawn>
	<spawn name="[dion13_2122_02]">
		<mesh>
			<!-- [dion13_2122_02]	{{41784;161100;-3467;-2267};{46612;160716;-3467;-2267};{51659;163606;-3467;-2267};{42227;163603;-3467;-2267}} -->
			<vertex x="41784" y="161100" minz="-3467" maxz="-2267" />
			<vertex x="46612" y="160716" minz="-3467" maxz="-2267" />
			<vertex x="51659" y="163606" minz="-3467" maxz="-2267" />
			<vertex x="42227" y="163603" minz="-3467" maxz="-2267" />
		</mesh>
		<npc id="20939" count="8" respawn="45" />
		<!-- [tanor_silenos_warrior]	pos=anywhere	total=8	respawn=45sec	Privates=[tanor_silenos_scout:tanor_silenos_scout:1:0sec;tanor_silenos_grunt:tanor_silenos_grunt:1:0sec;tanor_silenos:tanor_silenos:1:0sec] -->
		<npc id="20944" count="4" respawn="45" />
		<!-- [nightmare_lord]	pos=anywhere	total=4	respawn=45sec	Privates=[nightmare_keeper:nightmare_keeper:1:0sec;nightmare_keeper:nightmare_keeper:1:0sec;nightmare_guide:nightmare_guide:1:0sec] -->
	</spawn>
	<spawn name="[dion13_2122_03]">
		<mesh>
			<!-- [dion13_2122_03]	{{50358;162813;-2943;-2143};{54555;161502;-2943;-2143};{58663;163640;-2943;-2143};{51849;163652;-2943;-2143}} -->
			<vertex x="50358" y="162813" minz="-2943" maxz="-2143" />
			<vertex x="54555" y="161502" minz="-2943" maxz="-2143" />
			<vertex x="58663" y="163640" minz="-2943" maxz="-2143" />
			<vertex x="51849" y="163652" minz="-2943" maxz="-2143" />
		</mesh>
		<npc id="20939" count="2" respawn="45" />
		<!-- [tanor_silenos_warrior]	pos=anywhere	total=2	respawn=45sec	Privates=[tanor_silenos_scout:tanor_silenos_scout:1:0sec;tanor_silenos_grunt:tanor_silenos_grunt:1:0sec;tanor_silenos:tanor_silenos:1:0sec] -->
		<npc id="20944" count="4" respawn="45" />
		<!-- [nightmare_lord]	pos=anywhere	total=4	respawn=45sec	Privates=[nightmare_keeper:nightmare_keeper:1:0sec;nightmare_keeper:nightmare_keeper:1:0sec;nightmare_guide:nightmare_guide:1:0sec] -->
	</spawn>
	<spawn name="[dion13_2122_04]">
		<mesh>
			<!-- [dion13_2122_04]	{{56219;162213;-3729;-2429};{65262;157122;-3729;-2429};{65323;163590;-3729;-2429};{58759;163551;-3729;-2429}} -->
			<vertex x="56219" y="162213" minz="-3729" maxz="-2429" />
			<vertex x="65262" y="157122" minz="-3729" maxz="-2429" />
			<vertex x="65323" y="163590" minz="-3729" maxz="-2429" />
			<vertex x="58759" y="163551" minz="-3729" maxz="-2429" />
		</mesh>
		<npc id="20939" count="4" respawn="45" />
		<!-- [tanor_silenos_warrior]	pos=anywhere	total=4	respawn=45sec	Privates=[tanor_silenos_scout:tanor_silenos_scout:1:0sec;tanor_silenos_grunt:tanor_silenos_grunt:1:0sec;tanor_silenos:tanor_silenos:1:0sec] -->
		<npc id="20944" count="10" respawn="45" />
		<!-- [nightmare_lord]	pos=anywhere	total=10	respawn=45sec	Privates=[nightmare_keeper:nightmare_keeper:1:0sec;nightmare_keeper:nightmare_keeper:1:0sec;nightmare_guide:nightmare_guide:1:0sec] -->
		<npc id="20941" count="6" respawn="45" />
		<!-- [tanor_silenos_cheiftain]	pos=anywhere	total=6	respawn=45sec	Privates=[tanor_silenos_shaman:tanor_silenos_shaman:1:0sec;tanor_silenos_shaman:tanor_silenos_shaman:1:0sec;tanor_silenos_shaman:tanor_silenos_shaman:1:0sec] -->
	</spawn>
	<spawn name="[dion13_2122_05]">
		<mesh>
			<!-- [dion13_2122_05]	{{64250;146987;-3789;-2689};{65162;146870;-3789;-2689};{65143;155403;-3789;-2689};{63376;151753;-3789;-2689}} -->
			<vertex x="64250" y="146987" minz="-3789" maxz="-2689" />
			<vertex x="65162" y="146870" minz="-3789" maxz="-2689" />
			<vertex x="65143" y="155403" minz="-3789" maxz="-2689" />
			<vertex x="63376" y="151753" minz="-3789" maxz="-2689" />
		</mesh>
		<npc id="20939" count="2" respawn="45" />
		<!-- [tanor_silenos_warrior]	pos=anywhere	total=2	respawn=45sec	Privates=[tanor_silenos_scout:tanor_silenos_scout:1:0sec;tanor_silenos_grunt:tanor_silenos_grunt:1:0sec;tanor_silenos:tanor_silenos:1:0sec] -->
		<npc id="20944" count="2" respawn="45" />
		<!-- [nightmare_lord]	pos=anywhere	total=2	respawn=45sec	Privates=[nightmare_keeper:nightmare_keeper:1:0sec;nightmare_keeper:nightmare_keeper:1:0sec;nightmare_guide:nightmare_guide:1:0sec] -->
		<npc id="20941" count="1" respawn="45" />
		<!-- [tanor_silenos_cheiftain]	pos=anywhere	total=1	respawn=45sec	Privates=[tanor_silenos_shaman:tanor_silenos_shaman:1:0sec;tanor_silenos_shaman:tanor_silenos_shaman:1:0sec;tanor_silenos_shaman:tanor_silenos_shaman:1:0sec] -->
	</spawn>
	<spawn name="[dion13_2122_06]">
		<mesh>
			<!-- [dion13_2122_06]	{{63982;142779;-3789;-2689};{65167;141626;-3789;-2689};{65176;146649;-3789;-2689};{63736;144599;-3789;-2689}} -->
			<vertex x="63982" y="142779" minz="-3789" maxz="-2689" />
			<vertex x="65167" y="141626" minz="-3789" maxz="-2689" />
			<vertex x="65176" y="146649" minz="-3789" maxz="-2689" />
			<vertex x="63736" y="144599" minz="-3789" maxz="-2689" />
		</mesh>
		<npc id="20939" count="2" respawn="45" />
		<!-- [tanor_silenos_warrior]	pos=anywhere	total=2	respawn=45sec	Privates=[tanor_silenos_scout:tanor_silenos_scout:1:0sec;tanor_silenos_grunt:tanor_silenos_grunt:1:0sec;tanor_silenos:tanor_silenos:1:0sec] -->
		<npc id="20944" count="1" respawn="45" />
		<!-- [nightmare_lord]	pos=anywhere	total=1	respawn=45sec	Privates=[nightmare_keeper:nightmare_keeper:1:0sec;nightmare_keeper:nightmare_keeper:1:0sec;nightmare_guide:nightmare_guide:1:0sec] -->
	</spawn>
	<spawn name="[dion13_2122_08s]">
		<mesh>
			<!-- [dion13_2122_08s]	{{38161;162091;-3724;-2524};{41318;161797;-3724;-2524};{41918;163433;-3724;-2524};{37852;163429;-3724;-2524}} -->
			<vertex x="38161" y="162091" minz="-3724" maxz="-2524" />
			<vertex x="41318" y="161797" minz="-3724" maxz="-2524" />
			<vertex x="41918" y="163433" minz="-3724" maxz="-2524" />
			<vertex x="37852" y="163429" minz="-3724" maxz="-2524" />
		</mesh>
		<npc id="20939" count="3" respawn="45" />
		<!-- [tanor_silenos_warrior]	pos=anywhere	total=3	respawn=45sec	Privates=[tanor_silenos_scout:tanor_silenos_scout:1:0sec;tanor_silenos_grunt:tanor_silenos_grunt:1:0sec;tanor_silenos:tanor_silenos:1:0sec] -->
	</spawn>
	<spawn name="[dion13_2122_09s]">
		<mesh>
			<!-- [dion13_2122_09s]	{{45485;162041;-3276;-2376};{47721;161650;-3276;-2376};{48543;163425;-3276;-2376};{44375;163435;-3276;-2376}} -->
			<vertex x="45485" y="162041" minz="-3276" maxz="-2376" />
			<vertex x="47721" y="161650" minz="-3276" maxz="-2376" />
			<vertex x="48543" y="163425" minz="-3276" maxz="-2376" />
			<vertex x="44375" y="163435" minz="-3276" maxz="-2376" />
		</mesh>
		<npc id="20944" count="3" respawn="45" />
		<!-- [nightmare_lord]	pos=anywhere	total=3	respawn=45sec	Privates=[nightmare_keeper:nightmare_keeper:1:0sec;nightmare_keeper:nightmare_keeper:1:0sec;nightmare_guide:nightmare_guide:1:0sec] -->
	</spawn>
	<spawn name="[dion13_2122_10s]">
		<mesh>
			<!-- [dion13_2122_10s]	{{62282;159897;-3702;-2802};{64998;159112;-3702;-2802};{65021;162016;-3702;-2802};{61185;162615;-3702;-2802}} -->
			<vertex x="62282" y="159897" minz="-3702" maxz="-2802" />
			<vertex x="64998" y="159112" minz="-3702" maxz="-2802" />
			<vertex x="65021" y="162016" minz="-3702" maxz="-2802" />
			<vertex x="61185" y="162615" minz="-3702" maxz="-2802" />
		</mesh>
		<npc id="20941" count="3" respawn="45" />
		<!-- [tanor_silenos_cheiftain]	pos=anywhere	total=3	respawn=45sec	Privates=[tanor_silenos_shaman:tanor_silenos_shaman:1:0sec;tanor_silenos_shaman:tanor_silenos_shaman:1:0sec;tanor_silenos_shaman:tanor_silenos_shaman:1:0sec] -->
	</spawn>
	<spawn name="[ssq06_npc2122_f21]" event_name="[ssq_seal2_dawn]">
		<npc id="31170" count="1" respawn="60" pos="39872 144193 -3707 0" />
		<!-- [emblem_of_dawn]	pos={39872;144193;-3707;0}	total=1	respawn=1min -->
	</spawn>
	<spawn name="[ssq06_npc2122_f22]" event_name="[ssq_seal2_twilight]">
		<npc id="31171" count="1" respawn="60" pos="39872 144193 -3707 0" />
		<!-- [emblem_of_dusk]	pos={39872;144193;-3707;0}	total=1	respawn=1min -->
	</spawn>
	<spawn name="[ssq06_npc2122_tw11]" event_name="[ssq_seal2_twilight]">
		<npc id="31126" count="1" respawn="60" pos="-53145 -250500 -7904 0" />
		<!-- [blacksmith_of_mammon]	pos={-53145;-250500;-7904;0}	total=1	respawn=1min -->
	</spawn>
	<spawn name="[ssq06_npc2122_da11]" event_name="[ssq_seal2_dawn]">
		<npc id="31126" count="1" respawn="60" pos="43088 143712 -5379 0" />
		<!-- [blacksmith_of_mammon]	pos={43088;143712;-5379;0}	total=1	respawn=1min	ai_parameters={[PosX1]=[114000];[PosY1]=[84320];[PosZ1]=[-6539];[PosX2]=[77760];[PosY2]=[78176];[PosZ2]=[-5123];[PosX3]=[43088];[PosY3]=[143712];[PosZ3]=[-5379]} -->
	</spawn>
	<spawn name="[dion02_mb2122_01]">
		<mesh>
			<!-- [dion02_mb2122_01]	{{53151;142897;-3932;-3332};{53548;142749;-3932;-3332};{54119;142852;-3932;-3332};{53643;144591;-3932;-3332};{53200;144369;-3932;-3332};{52850;143748;-3932;-3332}} -->
			<vertex x="53151" y="142897" minz="-3932" maxz="-3332" />
			<vertex x="53548" y="142749" minz="-3932" maxz="-3332" />
			<vertex x="54119" y="142852" minz="-3932" maxz="-3332" />
			<vertex x="53643" y="144591" minz="-3932" maxz="-3332" />
			<vertex x="53200" y="144369" minz="-3932" maxz="-3332" />
			<vertex x="52850" y="143748" minz="-3932" maxz="-3332" />
		</mesh>
		<npc id="25385" count="1" respawn="129600" respawn_rand="86400" />
		<!-- [demon_tempest]	pos=anywhere	total=1	respawn=36hour	respawn_rand=24hour	dbname=[demon_tempest]	dbsaving={death_time;parameters} -->
	</spawn>
	<spawn name="[dion02_mb2122_02]">
		<mesh>
			<!-- [dion02_mb2122_02]	{{50325;146283;-3677;-3077};{50978;145946;-3677;-3077};{51400;146676;-3677;-3077};{51137;147486;-3677;-3077};{50574;147430;-3677;-3077}} -->
			<vertex x="50325" y="146283" minz="-3677" maxz="-3077" />
			<vertex x="50978" y="145946" minz="-3677" maxz="-3077" />
			<vertex x="51400" y="146676" minz="-3677" maxz="-3077" />
			<vertex x="51137" y="147486" minz="-3677" maxz="-3077" />
			<vertex x="50574" y="147430" minz="-3677" maxz="-3077" />
		</mesh>
		<npc id="25118" count="1" respawn="129600" respawn_rand="86400" />
		<!-- [warden_guillotine]	pos=anywhere	total=1	respawn=36hour	respawn_rand=24hour	dbname=[warden_guillotine]	dbsaving={death_time;parameters} -->
	</spawn>
	<spawn name="[dion02_mb2122_03]">
		<mesh>
			<!-- [dion02_mb2122_03]	{{42227;152067;-2894;-2294};{43611;152017;-2894;-2294};{43446;152927;-2894;-2294};{42965;152958;-2894;-2294}} -->
			<vertex x="42227" y="152067" minz="-2894" maxz="-2294" />
			<vertex x="43611" y="152017" minz="-2894" maxz="-2294" />
			<vertex x="43446" y="152927" minz="-2894" maxz="-2294" />
			<vertex x="42965" y="152958" minz="-2894" maxz="-2294" />
		</mesh>
		<npc id="25223" count="1" respawn="129600" respawn_rand="86400" />
		<!-- [soul_collector_acheron]	pos=anywhere	total=1	respawn=36hour	respawn_rand=24hour	dbname=[soul_collector_acheron]	dbsaving={death_time;parameters} -->
	</spawn>
	<spawn name="[ssq06_mb2122_01]">
		<mesh>
			<!-- [ssq06_mb2122_01]	{{50882;153506;-3608;-3008};{51369;153158;-3608;-3008};{52226;154135;-3608;-3008};{51144;155137;-3608;-3008}} -->
			<vertex x="50882" y="153506" minz="-3608" maxz="-3008" />
			<vertex x="51369" y="153158" minz="-3608" maxz="-3008" />
			<vertex x="52226" y="154135" minz="-3608" maxz="-3008" />
			<vertex x="51144" y="155137" minz="-3608" maxz="-3008" />
		</mesh>
		<npc id="25383" count="1" respawn="129600" respawn_rand="86400" />
		<!-- [revenant_of_sir_calibus]	pos=anywhere	total=1	respawn=36hour	respawn_rand=24hour	dbname=[revenant_of_sir_calibus]	dbsaving={death_time;parameters} -->
	</spawn>
	<spawn name="[dion01_qm2023_03]">
		<mesh>
			<!-- [dion01_qm2023_03]	{{56743;141465;-2829;-1929};{57926;142725;-2829;-1929};{57423;143831;-2829;-1929};{56481;142459;-2829;-1929}} -->
			<vertex x="56743" y="141465" minz="-2829" maxz="-1929" />
			<vertex x="57926" y="142725" minz="-2829" maxz="-1929" />
			<vertex x="57423" y="143831" minz="-2829" maxz="-1929" />
			<vertex x="56481" y="142459" minz="-2829" maxz="-1929" />
		</mesh>
		<npc id="27099" count="8" respawn="600" />
		<!-- [nameless_revenant]	pos=anywhere	total=8	respawn=10min -->
	</spawn>
	<spawn name="[dion01_qm2023_04]">
		<mesh>
			<!-- [dion01_qm2023_04]	{{53205;142949;-3907;-3507};{54067;143000;-3907;-3507};{53601;144535;-3907;-3507};{52923;143673;-3907;-3507}} -->
			<vertex x="53205" y="142949" minz="-3907" maxz="-3507" />
			<vertex x="54067" y="143000" minz="-3907" maxz="-3507" />
			<vertex x="53601" y="144535" minz="-3907" maxz="-3507" />
			<vertex x="52923" y="143673" minz="-3907" maxz="-3507" />
		</mesh>
		<npc id="27099" count="8" respawn="600" />
		<!-- [nameless_revenant]	pos=anywhere	total=8	respawn=10min -->
	</spawn>
	<spawn name="[dion09_npc2023_10]">
		<npc id="30979" count="1" respawn="60" pos="50693 158674 376 0" />
		<!-- [holy_ark_3]	pos={50693;158674;376;0}	total=1	respawn=1min -->
	</spawn>
	<spawn name="[dion02_npc2122_01]">
		<npc id="30631" count="1" respawn="60" pos="44694 146500 -3682 12288" />
		<!-- [warden_roderik]	pos={44694;146500;-3682;12288}	total=1	respawn=1min -->
	</spawn>
	<spawn name="[dion02_npc2122_02]">
		<npc id="30632" count="1" respawn="60" pos="45411 149100 -3681 42000" />
		<!-- [warden_endrigo]	pos={45411;149100;-3681;42000}	total=1	respawn=1min -->
	</spawn>
	<spawn name="[ssq06_npc2122_02]">
		<npc id="31114" count="1" respawn="60" pos="42608 143952 -5379 32500" />
		<!-- [enter_catacomb1]	pos={42608;143952;-5379;32500}	total=1	respawn=1min -->
	</spawn>
	<spawn name="[dion15_tb2122_03s]" event_name="[treasure_box]">
		<mesh>
			<!-- [dion15_tb2122_03s]	{{33268;136204;-3341;-2741};{35377;135291;-3341;-2741};{35754;137587;-3341;-2741};{33163;140018;-3341;-2741}} -->
			<vertex x="33268" y="136204" minz="-3341" maxz="-2741" />
			<vertex x="35377" y="135291" minz="-3341" maxz="-2741" />
			<vertex x="35754" y="137587" minz="-3341" maxz="-2741" />
			<vertex x="33163" y="140018" minz="-3341" maxz="-2741" />
		</mesh>
		<npc id="18266" count="1" respawn="60" />
		<!-- [treasure_box_24]	pos=anywhere	total=2	respawn=60sec -->
		<npc id="21802" count="1" respawn="60" />
		<!-- [mimic_24]	pos=anywhere	total=2	respawn=60sec -->
	</spawn>
	<spawn name="[dion06_tb2122_20s]" event_name="[treasure_box]">
		<mesh>
			<!-- [dion06_tb2122_20s]	{{40207;145191;-3960;-3360};{41090;146457;-3960;-3360};{40727;147323;-3960;-3360};{38391;147509;-3960;-3360};{38314;146511;-3960;-3360};{39653;145086;-3960;-3360}} -->
			<vertex x="40207" y="145191" minz="-3960" maxz="-3360" />
			<vertex x="41090" y="146457" minz="-3960" maxz="-3360" />
			<vertex x="40727" y="147323" minz="-3960" maxz="-3360" />
			<vertex x="38391" y="147509" minz="-3960" maxz="-3360" />
			<vertex x="38314" y="146511" minz="-3960" maxz="-3360" />
			<vertex x="39653" y="145086" minz="-3960" maxz="-3360" />
		</mesh>
		<npc id="18265" count="1" respawn="60" />
		<!-- [treasure_box_21]	pos=anywhere	total=1	respawn=60sec -->
		<npc id="21801" count="1" respawn="60" />
		<!-- [mimic_21]	pos=anywhere	total=1	respawn=60sec -->
	</spawn>
	<spawn name="[dion06_tb2122_21s]" event_name="[treasure_box]">
		<mesh>
			<!-- [dion06_tb2122_21s]	{{40684;148647;-3960;-3360};{41166;149292;-3960;-3360};{40777;150866;-3960;-3360};{39042;150811;-3960;-3360};{37668;149673;-3960;-3360};{38100;149070;-3960;-3360}} -->
			<vertex x="40684" y="148647" minz="-3960" maxz="-3360" />
			<vertex x="41166" y="149292" minz="-3960" maxz="-3360" />
			<vertex x="40777" y="150866" minz="-3960" maxz="-3360" />
			<vertex x="39042" y="150811" minz="-3960" maxz="-3360" />
			<vertex x="37668" y="149673" minz="-3960" maxz="-3360" />
			<vertex x="38100" y="149070" minz="-3960" maxz="-3360" />
		</mesh>
		<npc id="18265" count="1" respawn="60" />
		<!-- [treasure_box_21]	pos=anywhere	total=1	respawn=60sec -->
		<npc id="21801" count="1" respawn="60" />
		<!-- [mimic_21]	pos=anywhere	total=1	respawn=60sec -->
	</spawn>
	<spawn name="[dion02_tb2122_23]" event_name="[treasure_box]">
		<mesh>
			<!-- [dion02_tb2122_23]	{{42857;141840;-3383;-2783};{45622;140341;-3383;-2783};{49682;140637;-3383;-2783};{43661;144493;-3383;-2783};{42221;144692;-3383;-2783};{41750;143115;-3383;-2783}} -->
			<vertex x="42857" y="141840" minz="-3383" maxz="-2783" />
			<vertex x="45622" y="140341" minz="-3383" maxz="-2783" />
			<vertex x="49682" y="140637" minz="-3383" maxz="-2783" />
			<vertex x="43661" y="144493" minz="-3383" maxz="-2783" />
			<vertex x="42221" y="144692" minz="-3383" maxz="-2783" />
			<vertex x="41750" y="143115" minz="-3383" maxz="-2783" />
		</mesh>
		<npc id="18267" count="1" respawn="60" />
		<!-- [treasure_box_27]	pos=anywhere	total=3	respawn=60sec -->
		<npc id="21803" count="1" respawn="60" />
		<!-- [mimic_27]	pos=anywhere	total=3	respawn=60sec -->
		<npc id="18268" count="1" respawn="60" />
		<!-- [treasure_box_30]	pos=anywhere	total=3	respawn=60sec -->
		<npc id="21804" count="1" respawn="60" />
		<!-- [mimic_30]	pos=anywhere	total=3	respawn=60sec -->
	</spawn>
	<spawn name="[dion02_tb2122_24]" event_name="[treasure_box]">
		<mesh>
			<!-- [dion02_tb2122_24]	{{44744;145274;-3838;-3238};{48911;142988;-3838;-3238};{50804;145462;-3838;-3238};{47162;146946;-3838;-3238};{45026;146381;-3838;-3238}} -->
			<vertex x="44744" y="145274" minz="-3838" maxz="-3238" />
			<vertex x="48911" y="142988" minz="-3838" maxz="-3238" />
			<vertex x="50804" y="145462" minz="-3838" maxz="-3238" />
			<vertex x="47162" y="146946" minz="-3838" maxz="-3238" />
			<vertex x="45026" y="146381" minz="-3838" maxz="-3238" />
		</mesh>
		<npc id="18267" count="1" respawn="60" />
		<!-- [treasure_box_27]	pos=anywhere	total=3	respawn=60sec -->
		<npc id="21803" count="1" respawn="60" />
		<!-- [mimic_27]	pos=anywhere	total=3	respawn=60sec -->
		<npc id="18268" count="1" respawn="60" />
		<!-- [treasure_box_30]	pos=anywhere	total=3	respawn=60sec -->
		<npc id="21804" count="1" respawn="60" />
		<!-- [mimic_30]	pos=anywhere	total=3	respawn=60sec -->
		<npc id="18269" count="1" respawn="60" />
		<!-- [treasure_box_33]	pos=anywhere	total=3	respawn=60sec -->
		<npc id="21805" count="1" respawn="60" />
		<!-- [mimic_33]	pos=anywhere	total=3	respawn=60sec -->
	</spawn>
	<spawn name="[dion02_tb2122_29]" event_name="[treasure_box]">
		<mesh>
			<!-- [dion02_tb2122_29]	{{45699;151349;-2946;-2446};{48307;150431;-2946;-2446};{50400;154088;-2946;-2446};{47523;155433;-2946;-2446};{46010;154313;-2946;-2446};{44995;152326;-2946;-2446}} -->
			<vertex x="45699" y="151349" minz="-2946" maxz="-2446" />
			<vertex x="48307" y="150431" minz="-2946" maxz="-2446" />
			<vertex x="50400" y="154088" minz="-2946" maxz="-2446" />
			<vertex x="47523" y="155433" minz="-2946" maxz="-2446" />
			<vertex x="46010" y="154313" minz="-2946" maxz="-2446" />
			<vertex x="44995" y="152326" minz="-2946" maxz="-2446" />
		</mesh>
		<npc id="18267" count="1" respawn="60" />
		<!-- [treasure_box_27]	pos=anywhere	total=3	respawn=60sec -->
		<npc id="21803" count="1" respawn="60" />
		<!-- [mimic_27]	pos=anywhere	total=3	respawn=60sec -->
		<npc id="18268" count="1" respawn="60" />
		<!-- [treasure_box_30]	pos=anywhere	total=3	respawn=60sec -->
		<npc id="21804" count="1" respawn="60" />
		<!-- [mimic_30]	pos=anywhere	total=3	respawn=60sec -->
	</spawn>
	<spawn name="[dion02_tb2122_32]" event_name="[treasure_box]">
		<mesh>
			<!-- [dion02_tb2122_32]	{{55469;149586;-2582;-2082};{56313;152034;-2582;-2082};{54503;154048;-2582;-2082};{53433;153653;-2582;-2082};{50028;149894;-2582;-2082};{52371;147614;-2582;-2082}} -->
			<vertex x="55469" y="149586" minz="-2582" maxz="-2082" />
			<vertex x="56313" y="152034" minz="-2582" maxz="-2082" />
			<vertex x="54503" y="154048" minz="-2582" maxz="-2082" />
			<vertex x="53433" y="153653" minz="-2582" maxz="-2082" />
			<vertex x="50028" y="149894" minz="-2582" maxz="-2082" />
			<vertex x="52371" y="147614" minz="-2582" maxz="-2082" />
		</mesh>
		<npc id="18266" count="1" respawn="60" />
		<!-- [treasure_box_24]	pos=anywhere	total=3	respawn=60sec -->
		<npc id="21802" count="1" respawn="60" />
		<!-- [mimic_24]	pos=anywhere	total=3	respawn=60sec -->
		<npc id="18267" count="1" respawn="60" />
		<!-- [treasure_box_27]	pos=anywhere	total=3	respawn=60sec -->
		<npc id="21803" count="1" respawn="60" />
		<!-- [mimic_27]	pos=anywhere	total=3	respawn=60sec -->
	</spawn>
	<spawn name="[dion02_tb2122_33]" event_name="[treasure_box]">
		<mesh>
			<!-- [dion02_tb2122_33]	{{51744;145023;-3253;-2453};{56485;145730;-3253;-2453};{56270;148733;-3253;-2453};{52646;146960;-3253;-2453}} -->
			<vertex x="51744" y="145023" minz="-3253" maxz="-2453" />
			<vertex x="56485" y="145730" minz="-3253" maxz="-2453" />
			<vertex x="56270" y="148733" minz="-3253" maxz="-2453" />
			<vertex x="52646" y="146960" minz="-3253" maxz="-2453" />
		</mesh>
		<npc id="18266" count="1" respawn="60" />
		<!-- [treasure_box_24]	pos=anywhere	total=3	respawn=60sec -->
		<npc id="21802" count="1" respawn="60" />
		<!-- [mimic_24]	pos=anywhere	total=3	respawn=60sec -->
		<npc id="18267" count="1" respawn="60" />
		<!-- [treasure_box_27]	pos=anywhere	total=3	respawn=60sec -->
		<npc id="21803" count="1" respawn="60" />
		<!-- [mimic_27]	pos=anywhere	total=3	respawn=60sec -->
	</spawn>
</list>